{
    "title": "td-vocab-format--BearerSecurityScheme",
    "description": "format: Specifies format of security authentication information (one of jwt, jwe, or jws). MUST be included. Type: string.",
    "$schema ": "http://json-schema.org/draft-06/schema#",
    "is-complex": false,
    "type": "object",
    "properties": {
        "securityDefinitions": {
            "type": "object",
            "minProperties": 1,
            "additionalProperties": {
                "$ref": "#/definitions/securityScheme"
            }
        }
    },
    "required": [
        "securityDefinitions"
    ],
    "additionalProperties": true,
    "definitions": {
        "securityScheme": {
            "type": "object",
            "properties": {
                "description": {
                    "type": "string"
                },
                "proxy": {
                    "$ref": "#/definitions/url"
                },
                "scheme": {
                    "type": "string",
                    "enum": [
                        "bearer"
                    ]
                },
                "authorization": {
                    "$ref": "#/definitions/url"
                },
                "alg": {
                    "type": "string",
                    "enum": ["MD5", "ES256", "ES512-256"]
                },
                "format": {
                    "type": "string",
                    "enum": ["jwt", "jwe", "jws"]
                },
                "in": {
                    "type": "string",
                    "enum": ["header", "query", "body", "cookie"]
                },
                "name": {
                    "type": "string"
                }
            },
            "required": [
                "scheme","format"
            ]
        },
        "url": {
            "type": "string",
            "format": "uri-reference"
        }
    }
}
